Workbook

Sheet Dashboard
A1: E-Commerce Retail Sales Dashboard
A2: Sales, Profit & Customer Performance Analysis | 2025
A4: Total Revenue | D4: Total Profit | G4: Profit Margin | J4: Total Orders
A5: =SUM(Raw_Sales!M2:M501) -> 71615.2 | D5: =SUM(Raw_Sales!O2:O501) -> 30829.2 | G5: =D5/A5 -> 0.43048403 | J5: =COUNTA(Raw_Sales!A2:A501) -> 500

Sheet Pivot_Category
A3: Row Labels | B3: Sum of Revenue
A4: Electronics | B4: 27001.25
A5: Lifestyle | B5: 10176.35
A6: Office | B6: 32670
A7: Stationery | B7: 1767.6
A8: Grand Total | B8: 71615.2

Sheet Pivot_Region
A3: Row Labels | B3: Sum of Revenue
A4: Birmingham | B4: 15167.3
A5: Bristol | B5: 11287.55
A6: Leeds | B6: 12805.5
A7: London | B7: 10774.9
A8: Manchester | B8: 9160.35
A9: Sheffield | B9: 12419.6
A10: Grand Total | B10: 71615.2

Sheet Pivot_Segment
A3: Row Labels | B3: Sum of Revenue
A4: Consumer | B4: 26642.65
A5: Corporate | B5: 28867.8
A6: Small Business | B6: 16104.75
A7: Grand Total | B7: 71615.2

Sheet Pivot_Monthly
A3: Row Labels | B3: Sum of Revenue
A4: Jan | B4: 7549.7
A5: Feb | B5: 6510.35
A6: Mar | B6: 8453.05
A7: Apr | B7: 3278.1
A8: May | B8: 4653.7
A9: Jun | B9: 6335.4
A10: Jul | B10: 6533.1
A11: Aug | B11: 7620.1
A12: Sep | B12: 5106.55
A13: Oct | B13: 6803.75
A14: Nov | B14: 3698.15
A15: Dec | B15: 5073.25
A16: Grand Total | B16: 71615.2

Sheet Raw_Sales
A1: Order_ID | B1: Order_Date | C1: Customer_ID | D1: Product_ID | E1: Quantity | F1: Discount | G1: Product_Name | H1: Category | I1: Unit_Price | J1: Customer_Name | K1: Region | L1: Customer_Segment | M1: Revenue | N1: Cost | O1: Profit
A2: O0001 | B2: 45687 | C2: C031 | D2: P010 | E2: 1 | F2: 0 | G2: =_xlfn.XLOOKUP(D2,Products!$A$2:$A$11,Products!$B$2:$B$11) -> USB-C Hub | H2: =_xlfn.XLOOKUP(D2,Products!$A$2:$A$11,Products!$C$2:$C$11) -> Electronics | I2: =_xlfn.XLOOKUP(D2,Products!$A$2:$A$11,Products!$D$2:$D$11) -> 40 | J2: =_xlfn.XLOOKUP(C2,Customers!$A$2:$A$101,Customers!$B$2:$B$101) -> Customer 031 | K2: =_xlfn.XLOOKUP(C2,Customers!$A$2:$A$101,Customers!$C$2:$C$101) -> Birmingham | L2: =_xlfn.XLOOKUP(C2,Customers!$A$2:$A$101,Customers!$D$2:$D$101) -> Corporate | M2: =E2*I2*(1-F2) -> 40 | N2: =E2*_xlfn.XLOOKUP(D2,Products!$A$2:$A$11,Products!$E$2:$E$11) -> 19 | O2: =M2-N2 -> 21
A3: O0002 | B3: 45906 | C3: C009 | D3: P009 | E3: 2 | F3: 0.05 | G3: =_xlfn.XLOOKUP(D3,Products!$A$2:$A$11,Products!$B$2:$B$11) -> Office Chair | H3: =_xlfn.XLOOKUP(D3,Products!$A$2:$A$11,Products!$C$2:$C$11) -> Office | I3: =_xlfn.XLOOKUP(D3,Products!$A$2:$A$11,Products!$D$2:$D$11) -> 180 | J3: =_xlfn.XLOOKUP(C3,Customers!$A$2:$A$101,Customers!$B$2:$B$101) -> Customer 009 | K3: =_xlfn.XLOOKUP(C3,Customers!$A$2:$A$101,Customers!$C$2:$C$101) -> London | L3: =_xlfn.XLOOKUP(C3,Customers!$A$2:$A$101,Customers!$D$2:$D$101) -> Consumer | M3: =E3*I3*(1-F3) -> 342 | N3: =E3*_xlfn.XLOOKUP(D3,Products!$A$2:$A$11,Products!$E$2:$E$11) -> 210 | O3: =M3-N3 -> 132
A4: O0003 | B4: 45995 | C4: C061 | D4: P009 | E4: 2 | F4: 0.1 | G4: =_xlfn.XLOOKUP(D4,Products!$A$2:$A$11,Products!$B$2:$B$11) -> Office Chair | H4: =_xlfn.XLOOKUP(D4,Products!$A$2:$A$11,Products!$C$2:$C$11) -> Office | I4: =_xlfn.XLOOKUP(D4,Products!$A$2:$A$11,Products!$D$2:$D$11) -> 180 | J4: =_xlfn.XLOOKUP(C4,Customers!$A$2:$A$101,Customers!$B$2:$B$101) -> Customer 061 | K4: =_xlfn.XLOOKUP(C4,Customers!$A$2:$A$101,Customers!$C$2:$C$101) -> Leeds | L4: =_xlfn.XLOOKUP(C4,Customers!$A$2:$A$101,Customers!$D$2:$D$101) -> Corporate | M4: =E4*I4*(1-F4) -> 324 | N4: =E4*_xlfn.XLOOKUP(D4,Products!$A$2:$A$11,Products!$E$2:$E$11) -> 210 | O4: =M4-N4 -> 114
A5: O0004 | B5: 45928 | C5: C078 | D5: P007 | E5: 2 | F5: 0.05 | G5: =_xlfn.XLOOKUP(D5,Products!$A$2:$A$11,Products!$B$2:$B$11) -> Headphones | H5: =_xlfn.XLOOKUP(D5,Products!$A$2:$A$11,Products!$C$2:$C$11) -> Electronics | I5: =_xlfn.XLOOKUP(D5,Products!$A$2:$A$11,Products!$D$2:$D$11) -> 75 | J5: =_xlfn.XLOOKUP(C5,Customers!$A$2:$A$101,Customers!$B$2:$B$101) -> Customer 078 | K5: =_xlfn.XLOOKUP(C5,Customers!$A$2:$A$101,Customers!$C$2:$C$101) -> Leeds | L5: =_xlfn.XLOOKUP(C5,Customers!$A$2:$A$101,Customers!$D$2:$D$101) -> Corporate | M5: =E5*I5*(1-F5) -> 142.5 | N5: =E5*_xlfn.XLOOKUP(D5,Products!$A$2:$A$11,Products!$E$2:$E$11) -> 80 | O5: =M5-N5 -> 62.5
A6: O0005 | B6: 45817 | C6: C052 | D6: P006 | E6: 4 | F6: 0.15 | G6: =_xlfn.XLOOKUP(D6,Products!$A$2:$A$11,Products!$B$2:$B$11) -> Backpack | H6: =_xlfn.XLOOKUP(D6,Products!$A$2:$A$11,Products!$C$2:$C$11) -> Lifestyle | I6: =_xlfn.XLOOKUP(D6,Products!$A$2:$A$11,Products!$D$2:$D$11) -> 55 | J6: =_xlfn.XLOOKUP(C6,Customers!$A$2:$A$101,Customers!$B$2:$B$101) -> Customer 052 | K6: =_xlfn.XLOOKUP(C6,Customers!$A$2:$A$101,Customers!$C$2:$C$101) -> Bristol | L6: =_xlfn.XLOOKUP(C6,Customers!$A$2:$A$101,Customers!$D$2:$D$101) -> Consumer | M6: =E6*I6*(1-F6) -> 187 | N6: =E6*_xlfn.XLOOKUP(D6,Products!$A$2:$A$11,Products!$E$2:$E$11) -> 108 | O6: =M6-N6 -> 79
A7: O0006 | B7: 45719 | C7: C032 | D7: P004 | E7: 1 | F7: 0.1 | G7: =_xlfn.XLOOKUP(D7,Products!$A$2:$A$11,Products!$B$2:$B$11) -> Desk Lamp | H7: =_xlfn.XLOOKUP(D7,Products!$A$2:$A$11,Products!$C$2:$C$11) -> Office | I7: =_xlfn.XLOOKUP(D7,Products!$A$2:$A$11,Products!$D$2:$D$11) -> 30 | J7: =_xlfn.XLOOKUP(C7,Customers!$A$2:$A$101,Customers!$B$2:$B$101) -> Customer 032 | K7: =_xlfn.XLOOKUP(C7,Customers!$A$2:$A$101,Customers!$C$2:$C$101) -> Bristol | L7: =_xlfn.XLOOKUP(C7,Customers!$A$2:$A$101,Customers!$D$2:$D$101) -> Small Business | M7: =E7*I7*(1-F7) -> 27 | N7: =E7*_xlfn.XLOOKUP(D7,Products!$A$2:$A$11,Products!$E$2:$E$11) -> 15 | O7: =M7-N7 -> 12
A8: O0007 | B8: 45668 | C8: C076 | D8: P009 | E8: 2 | F8: 0.05 | G8: =_xlfn.XLOOKUP(D8,Products!$A$2:$A$11,Products!$B$2:$B$11) -> Office Chair | H8: =_xlfn.XLOOKUP(D8,Products!$A$2:$A$11,Products!$C$2:$C$11) -> Office | I8: =_xlfn.XLOOKUP(D8,Products!$A$2:$A$11,Products!$D$2:$D$11) -> 180 | J8: =_xlfn.XLOOKUP(C8,Customers!$A$2:$A$101,Customers!$B$2:$B$101) -> Customer 076 | K8: =_xlfn.XLOOKUP(C8,Customers!$A$2:$A$101,Customers!$C$2:$C$101) -> London | L8: =_xlfn.XLOOKUP(C8,Customers!$A$2:$A$101,Customers!$D$2:$D$101) -> Small Business | M8: =E8*I8*(1-F8) -> 342 | N8: =E8*_xlfn.XLOOKUP(D8,Products!$A$2:$A$11,Products!$E$2:$E$11) -> 210 | O8: =M8-N8 -> 132
A9: O0008 | B9: 45661 | C9: C010 | D9: P001 | E9: 2 | F9: 0 | G9: =_xlfn.XLOOKUP(D9,Products!$A$2:$A$11,Products!$B$2:$B$11) -> Laptop Stand | H9: =_xlfn.XLOOKUP(D9,Products!$A$2:$A$11,Products!$C$2:$C$11) -> Office | I9: =_xlfn.XLOOKUP(D9,Products!$A$2:$A$11,Products!$D$2:$D$11) -> 35 | J9: =_xlfn.XLOOKUP(C9,Customers!$A$2:$A$101,Customers!$B$2:$B$101) -> Customer 010 | K9: =_xlfn.XLOOKUP(C9,Customers!$A$2:$A$101,Customers!$C$2:$C$101) -> London | L9: =_xlfn.XLOOKUP(C9,Customers!$A$2:$A$101,Customers!$D$2:$D$101) -> Consumer | M9: =E9*I9*(1-F9) -> 70 | N9: =E9*_xlfn.XLOOKUP(D9,Products!$A$2:$A$11,Products!$E$2:$E$11) -> 40 | O9: =M9-N9 -> 30
A10: O0009 | B10: 45674 | C10: C043 | D10: P002 | E10: 5 | F10: 0.05 | G10: =_xlfn.XLOOKUP(D10,Products!$A$2:$A$11,Products!$B$2:$B$11) -> Wireless Mouse | H10: =_xlfn.XLOOKUP(D10,Products!$A$2:$A$11,Products!$C$2:$C$11) -> Electronics | I10: =_xlfn.XLOOKUP(D10,Products!$A$2:$A$11,Products!$D$2:$D$11) -> 25 | J10: =_xlfn.XLOOKUP(C10,Customers!$A$2:$A$101,Customers!$B$2:$B$101) -> Customer 043 | K10: =_xlfn.XLOOKUP(C10,Customers!$A$2:$A$101,Customers!$C$2:$C$101) -> Sheffield | L10: =_xlfn.XLOOKUP(C10,Customers!$A$2:$A$101,Customers!$D$2:$D$101) -> Small Business | M10: =E10*I10*(1-F10) -> 118.75 | N10: =E10*_xlfn.XLOOKUP(D10,Products!$A$2:$A$11,Products!$E$2:$E$11) -> 60 | O10: =M10-N10 -> 58.75
A11: O0010 | B11: 45800 | C11: C086 | D11: P008 | E11: 2 | F11: 0.05 | G11: =_xlfn.XLOOKUP(D11,Products!$A$2:$A$11,Products!$B$2:$B$11) -> Notebook Pack | H11: =_xlfn.XLOOKUP(D11,Products!$A$2:$A$11,Products!$C$2:$C$11) -> Stationery | I11: =_xlfn.XLOOKUP(D11,Products!$A$2:$A$11,Products!$D$2:$D$11) -> 12 | J11: =_xlfn.XLOOKUP(C11,Customers!$A$2:$A$101,Customers!$B$2:$B$101) -> Customer 086 | K11: =_xlfn.XLOOKUP(C11,Customers!$A$2:$A$101,Customers!$C$2:$C$101) -> Manchester | L11: =_xlfn.XLOOKUP(C11,Customers!$A$2:$A$101,Customers!$D$2:$D$101) -> Small Business | M11: =E11*I11*(1-F11) -> 22.8 | N11: =E11*_xlfn.XLOOKUP(D11,Products!$A$2:$A$11,Products!$E$2:$E$11) -> 10 | O11: =M11-N11 -> 12.8
A12: O0011 | B12: 45950 | C12: C074 | D12: P008 | E12: 2 | F12: 0.15 | G12: =_xlfn.XLOOKUP(D12,Products!$A$2:$A$11,Products!$B$2:$B$11) -> Notebook Pack | H12: =_xlfn.XLOOKUP(D12,Products!$A$2:$A$11,Products!$C$2:$C$11) -> Stationery | I12: =_xlfn.XLOOKUP(D12,Products!$A$2:$A$11,Products!$D$2:$D$11) -> 12 | J12: =_xlfn.XLOOKUP(C12,Customers!$A$2:$A$101,Customers!$B$2:$B$101) -> Customer 074 | K12: =_xlfn.XLOOKUP(C12,Customers!$A$2:$A$101,Customers!$C$2:$C$101) -> Manchester | L12: =_xlfn.XLOOKUP(C12,Customers!$A$2:$A$101,Customers!$D$2:$D$101) -> Corporate | M12: =E12*I12*(1-F12) -> 20.4 | N12: =E12*_xlfn.XLOOKUP(D12,Products!$A$2:$A$11,Products!$E$2:$E$11) -> 10 | O12: =M12-N12 -> 10.4
A13: O0012 | B13: 45866 | C13: C025 | D13: P002 | E13: 1 | F13: 0.15 | G13: =_xlfn.XLOOKUP(D13,Products!$A$2:$A$11,Products!$B$2:$B$11) -> Wireless Mouse | H13: =_xlfn.XLOOKUP(D13,Products!$A$2:$A$11,Products!$C$2:$C$11) -> Electronics | I13: =_xlfn.XLOOKUP(D13,Products!$A$2:$A$11,Products!$D$2:$D$11) -> 25 | J13: =_xlfn.XLOOKUP(C13,Customers!$A$2:$A$101,Customers!$B$2:$B$101) -> Customer 025 | K13: =_xlfn.XLOOKUP(C13,Customers!$A$2:$A$101,Customers!$C$2:$C$101) -> Birmingham | L13: =_xlfn.XLOOKUP(C13,Customers!$A$2:$A$101,Customers!$D$2:$D$101) -> Small Business | M13: =E13*I13*(1-F13) -> 21.25 | N13: =E13*_xlfn.XLOOKUP(D13,Products!$A$2:$A$11,Products!$E$2:$E$11) -> 12 | O13: =M13-N13 -> 9.25
... A501: O0500 | B501: 45662 | C501: C028 | D501: P009 | E501: 4 | F501: 0.1 | G501: =_xlfn.XLOOKUP(D501,Products!$A$2:$A$11,Products!$B$2:$B$11) -> Office Chair | H501: =_xlfn.XLOOKUP(D501,Products!$A$2:$A$11,Products!$C$2:$C$11) -> Office | I501: =_xlfn.XLOOKUP(D501,Products!$A$2:$A$11,Products!$D$2:$D$11) -> 180 | J501: =_xlfn.XLOOKUP(C501,Customers!$A$2:$A$101,Customers!$B$2:$B$101) -> Customer 028 | K501: =_xlfn.XLOOKUP(C501,Customers!$A$2:$A$101,Customers!$C$2:$C$101) -> Leeds | L501: =_xlfn.XLOOKUP(C501,Customers!$A$2:$A$101,Customers!$D$2:$D$101) -> Corporate | M501: =E501*I501*(1-F501) -> 648 | N501: =E501*_xlfn.XLOOKUP(D501,Products!$A$2:$A$11,Products!$E$2:$E$11) -> 420 | O501: =M501-N501 -> 228

Sheet Products
A1: Product_ID | B1: Product_Name | C1: Category | D1: Unit_Price | E1: Unit_Cost
A2: P001 | B2: Laptop Stand | C2: Office | D2: 35 | E2: 20
A3: P002 | B3: Wireless Mouse | C3: Electronics | D3: 25 | E3: 12
A4: P003 | B4: Keyboard | C4: Electronics | D4: 45 | E4: 22
A5: P004 | B5: Desk Lamp | C5: Office | D5: 30 | E5: 15
A6: P005 | B6: Water Bottle | C6: Lifestyle | D6: 18 | E6: 7
A7: P006 | B7: Backpack | C7: Lifestyle | D7: 55 | E7: 27
A8: P007 | B8: Headphones | C8: Electronics | D8: 75 | E8: 40
A9: P008 | B9: Notebook Pack | C9: Stationery | D9: 12 | E9: 5
A10: P009 | B10: Office Chair | C10: Office | D10: 180 | E10: 105
A11: P010 | B11: USB-C Hub | C11: Electronics | D11: 40 | E11: 19

Sheet Customers
A1: Customer_ID | B1: Customer_Name | C1: Region | D1: Customer_Segment
A2: C001 | B2: Customer 001 | C2: Sheffield | D2: Consumer
A3: C002 | B3: Customer 002 | C3: London | D3: Corporate
A4: C003 | B4: Customer 003 | C4: Birmingham | D4: Consumer
A5: C004 | B5: Customer 004 | C5: Manchester | D5: Consumer
A6: C005 | B6: Customer 005 | C6: Sheffield | D6: Consumer
A7: C006 | B7: Customer 006 | C7: Sheffield | D7: Corporate
A8: C007 | B8: Customer 007 | C8: Bristol | D8: Consumer
A9: C008 | B9: Customer 008 | C9: Bristol | D9: Small Business
A10: C009 | B10: Customer 009 | C10: London | D10: Consumer
A11: C010 | B11: Customer 010 | C11: London | D11: Consumer
A12: C011 | B12: Customer 011 | C12: Manchester | D12: Corporate
... A101: C100 | B101: Customer 100 | C101: Birmingham | D101: Consumer

Sheet Instructions
A1: Item | B1: Details
A2: Project | B2: Retail Sales & Business Performance Analysis | Excel
A3: Dataset | B3: 500 retail transactions, 100 customers and 10 products covering 2025.
A4: Goal | B4: Use Excel to clean, enrich, analyse and visualise retail sales performance.
A5: Next | B5: Use XLOOKUP to enrich Raw_Sales with product and customer information.
A6: Then | B6: Calculate Revenue and Cost, build Pivot Tables, KPIs, charts and a dashboard.
